Metadata-Version: 2.1
Name: devtools_json_escape
Version: 1.0.1
Summary: JSON string escape/unescape
Home-page: https://devtools.at/tools/json-escape
Author: DevTools.at
Author-email: hello@devtools.at
Project-URL: Homepage, https://devtools.at/tools/json-escape
Project-URL: Repository, https://github.com/devtools-at/json-escape
Classifier: Development Status :: 4 - Beta
Classifier: Intended Audience :: Developers
Classifier: License :: OSI Approved :: MIT License
Classifier: Programming Language :: Python :: 3
Requires-Python: >=3.8
